nbfinder/__init__.py
nbfinder/find_notebook.py
nbfinder/notebook_finder.py
nbfinder/notebook_loader.py
nbfinder-1.0.2.dist-info/DESCRIPTION.rst
nbfinder-1.0.2.dist-info/METADATA
nbfinder-1.0.2.dist-info/RECORD
nbfinder-1.0.2.dist-info/WHEEL
nbfinder-1.0.2.dist-info/metadata.json
nbfinder-1.0.2.dist-info/top_level.txt
