Metadata-Version: 2.0
Name: nbfinder
Version: 1.0.2
Summary: Import Jupyter Notebooks as Modules
Home-page: https://github.com/hadim/nbfinder
Author: Hadrien Mary
Author-email: hadrien.mary@gmail.com
License: MIT
Download-URL: https://github.com/hadim/nbfinder
Platform: UNKNOWN
Classifier: Development Status :: 5 - Production/Stable
Classifier: License :: OSI Approved :: MIT License
Classifier: Operating System :: OS Independent
Classifier: Programming Language :: Python
Classifier: Programming Language :: Python :: 2
Classifier: Programming Language :: Python :: 2.7
Classifier: Programming Language :: Python :: 3
Classifier: Programming Language :: Python :: 3.5
Classifier: Programming Language :: Python :: 3.6
Requires-Dist: ipython
Requires-Dist: nbformat
